<?xml version="1.0" encoding="utf-8"?><odds_feed updated="29.05.2015 06:30:22" sport="soccer"><league country="asia" id="2855" name="Asia: Afc Champions League - Play Offs" sub_id="28551"><match alternate_id="" alternate_id_2="4337877" date="25.08.2015" id="" static_id="25081523490632343303" status="10:00" time="10:00"><home alternate_id="" id="2349063" name="Al Ahli Dubai (Uae)"></home><away alternate_id="" id="2343303" name="Naft Tehran (Irn)"></away></match><match alternate_id="" alternate_id_2="4337863" date="25.08.2015" id="" static_id="25081523439762339882" status="10:00" time="10:00"><home alternate_id="" id="2343976" name="G-Osaka (Jpn)"></home><away alternate_id="536380381377" id="2339882" name="Guangzhou Evergrande (Chn)"></away></match><match alternate_id="" alternate_id_2="4337785" date="25.08.2015" id="" static_id="25081523439852344173" status="10:00" time="10:00"><home alternate_id="" id="2343985" name="Kashiwa (Jpn)"></home><away alternate_id="536380381374" id="2344173" name="Jeonbuk (Kor)"></away></match><match alternate_id="" alternate_id_2="4337810" date="25.08.2015" id="" static_id="25081523463402346834" status="10:00" time="10:00"><home alternate_id="" id="2346340" name="Lakhwiya (Qat)"></home><away alternate_id="" id="2346834" name="Al-Hilal (Sau)"></away></match><match alternate_id="" alternate_id_2="4337811" date="15.09.2015" id="" static_id="15091523468342346340" status="10:00" time="10:00"><home alternate_id="" id="2346834" name="Al-Hilal (Sau)"></home><away alternate_id="" id="2346340" name="Lakhwiya (Qat)"></away></match><match alternate_id="" alternate_id_2="4337864" date="15.09.2015" id="" static_id="15091523398822343976" status="10:00" time="10:00"><home alternate_id="536380381377" id="2339882" name="Guangzhou Evergrande (Chn)"></home><away alternate_id="" id="2343976" name="G-Osaka (Jpn)"></away></match><match alternate_id="" alternate_id_2="4337786" date="15.09.2015" id="" static_id="15091523441732343985" status="10:00" time="10:00"><home alternate_id="536380381374" id="2344173" name="Jeonbuk (Kor)"></home><away alternate_id="" id="2343985" name="Kashiwa (Jpn)"></away></match><match alternate_id="" alternate_id_2="4337878" date="15.09.2015" id="" static_id="15091523433032349063" status="10:00" time="10:00"><home alternate_id="" id="2343303" name="Naft Tehran (Irn)"></home><away alternate_id="" id="2349063" name="Al Ahli Dubai (Uae)"></away></match></league><league country="asia" id="4374" name="Asia: East Asian Championship" sub_id="43740"><match alternate_id="" alternate_id_2="4292099" date="02.08.2015" id="" static_id="02081523441322343957" status="10:20" time="10:20"><home alternate_id="536380381400" id="2344132" name="North Korea"></home><away alternate_id="536380381127" id="2343957" name="Japan"></away></match><match alternate_id="" alternate_id_2="4284419" date="02.08.2015" id="" static_id="02081523398602344136" status="13:00" time="13:00"><home alternate_id="536380381401" id="2339860" name="China"></home><away alternate_id="536380381138" id="2344136" name="South Korea"></away></match><match alternate_id="" alternate_id_2="4284420" date="05.08.2015" id="" static_id="05081523439572344136" status="10:20" time="10:20"><home alternate_id="536380381127" id="2343957" name="Japan"></home><away alternate_id="536380381138" id="2344136" name="South Korea"></away></match><match alternate_id="" alternate_id_2="4292100" date="05.08.2015" id="" static_id="05081523398602344132" status="13:00" time="13:00"><home alternate_id="536380381401" id="2339860" name="China"></home><away alternate_id="536380381400" id="2344132" name="North Korea"></away></match><match alternate_id="" alternate_id_2="4292101" date="09.08.2015" id="" static_id="09081523441362344132" status="09:10" time="09:10"><home alternate_id="536380381138" id="2344136" name="South Korea"></home><away alternate_id="536380381400" id="2344132" name="North Korea"></away></match><match alternate_id="" alternate_id_2="4284421" date="09.08.2015" id="" static_id="09081523398602343957" status="12:10" time="12:10"><home alternate_id="536380381401" id="2339860" name="China"></home><away alternate_id="536380381127" id="2343957" name="Japan"></away></match></league><league country="asia" id="4381" name="Asia: Southeast Asian Games" sub_id=""><match alternate_id="4129335" alternate_id_2="4337763" date="29.05.2015" id="4246875" static_id="29051523562802355839" status="08:00" time="08:00"><home alternate_id="" id="2356280" name="Brunei U23"></home><away alternate_id="" id="2355839" name="Vietnam U23"></away></match><match alternate_id="4129336" alternate_id_2="4337764" date="29.05.2015" id="4246876" static_id="29051523558542354719" status="12:30" time="12:30"><home alternate_id="" id="2355854" name="Laos U23"></home><away alternate_id="" id="2354719" name="Thailand U23"></away></match><match alternate_id="4129337" alternate_id_2="4337765" date="30.05.2015" id="4246877" static_id="30051523547172355837" status="12:30" time="12:30"><home alternate_id="" id="2354717" name="Malaysia U23"></home><away alternate_id="" id="2355837" name="East Timor U23"></away></match><match alternate_id="4129338" alternate_id_2="4337766" date="31.05.2015" id="4246878" static_id="31051523562802355854" status="12:30" time="12:30"><home alternate_id="" id="2356280" name="Brunei U23"></home><away alternate_id="" id="2355854" name="Laos U23"></away></match><match alternate_id="4129339" alternate_id_2="4337767" date="01.06.2015" id="4246879" static_id="" status="12:30" time="12:30"><home alternate_id="" id="" name="Philippines U23"></home><away alternate_id="" id="2344653" name="Singapore U23"></away></match><match alternate_id="4129340" alternate_id_2="4337768" date="01.06.2015" id="4246880" static_id="01061523547192355837" status="12:30" time="12:30"><home alternate_id="" id="2354719" name="Thailand U23"></home><away alternate_id="" id="2355837" name="East Timor U23"></away></match><match alternate_id="4129341" alternate_id_2="4337769" date="02.06.2015" id="4246881" static_id="" status="12:30" time="12:30"><home alternate_id="" id="" name="Myanmar U23"></home><away alternate_id="" id="2354718" name="Indonesia U23"></away></match><match alternate_id="4129342" alternate_id_2="4337770" date="02.06.2015" id="4246882" static_id="02061523558392354717" status="12:30" time="12:30"><home alternate_id="" id="2355839" name="Vietnam U23"></home><away alternate_id="" id="2354717" name="Malaysia U23"></away></match><match alternate_id="4129343" alternate_id_2="4337771" date="03.06.2015" id="4246883" static_id="" status="12:30" time="12:30"><home alternate_id="" id="" name="Cambodia U23"></home><away alternate_id="" id="" name="Philippines U23"></away></match><match alternate_id="4129493" alternate_id_2="4337772" date="03.06.2015" id="4247033" static_id="03061523558372356280" status="12:30" time="12:30"><home alternate_id="" id="2355837" name="East Timor U23"></home><away alternate_id="" id="2356280" name="Brunei U23"></away></match><match alternate_id="4129344" alternate_id_2="4337773" date="04.06.2015" id="4246884" static_id="04061523547172354719" status="08:00" time="08:00"><home alternate_id="" id="2354717" name="Malaysia U23"></home><away alternate_id="" id="2354719" name="Thailand U23"></away></match><match alternate_id="4129345" alternate_id_2="4337774" date="04.06.2015" id="4246885" static_id="" status="12:30" time="12:30"><home alternate_id="" id="2344653" name="Singapore U23"></home><away alternate_id="" id="" name="Myanmar U23"></away></match><match alternate_id="4129346" alternate_id_2="4337775" date="04.06.2015" id="4246886" static_id="04061523558392355854" status="12:30" time="12:30"><home alternate_id="" id="2355839" name="Vietnam U23"></home><away alternate_id="" id="2355854" name="Laos U23"></away></match><match alternate_id="4129347" alternate_id_2="4337776" date="06.06.2015" id="4246887" static_id="" status="12:30" time="12:30"><home alternate_id="" id="2354718" name="Indonesia U23"></home><away alternate_id="" id="" name="Cambodia U23"></away></match><match alternate_id="4129494" alternate_id_2="4337777" date="06.06.2015" id="4247034" static_id="06061523547192356280" status="12:30" time="12:30"><home alternate_id="" id="2354719" name="Thailand U23"></home><away alternate_id="" id="2356280" name="Brunei U23"></away></match><match alternate_id="4129348" alternate_id_2="4337778" date="07.06.2015" id="4246888" static_id="07061523558372355839" status="12:30" time="12:30"><home alternate_id="" id="2355837" name="East Timor U23"></home><away alternate_id="" id="2355839" name="Vietnam U23"></away></match><match alternate_id="4129349" alternate_id_2="4337779" date="07.06.2015" id="4246889" static_id="" status="12:30" time="12:30"><home alternate_id="" id="" name="Philippines U23"></home><away alternate_id="" id="" name="Myanmar U23"></away></match><match alternate_id="4129350" alternate_id_2="4337780" date="08.06.2015" id="4246890" static_id="08061523562802354717" status="12:30" time="12:30"><home alternate_id="" id="2356280" name="Brunei U23"></home><away alternate_id="" id="2354717" name="Malaysia U23"></away></match><match alternate_id="4129350" alternate_id_2="4337781" date="08.06.2015" id="4246890" static_id="" status="12:30" time="12:30"><home alternate_id="" id="" name="Cambodia U23"></home><away alternate_id="" id="2344653" name="Singapore U23"></away></match><match alternate_id="4129351" alternate_id_2="4337782" date="09.06.2015" id="4246891" static_id="09061523558372355854" status="12:30" time="12:30"><home alternate_id="" id="2355837" name="East Timor U23"></home><away alternate_id="" id="2355854" name="Laos U23"></away></match></league></odds_feed>