<?xml version="1.0" encoding="utf-8"?><odds_feed updated="02.05.2015 15:31:02" sport="soccer"><league country="cameroon" id="2988" name="Cameroon: Elite One" sub_id="29880"><match alternate_id="" alternate_id_2="4324198" date="03.05.2015" id="" static_id="03051523397272339712" status="12:30" time="12:30"><home alternate_id="536380381678" id="2339727" name="Bafang"></home><away alternate_id="536380381683" id="2339712" name="Fovu Baham"></away></match><match alternate_id="" alternate_id_2="4324187" date="03.05.2015" id="" static_id="" status="14:30" time="14:30"><home alternate_id="536380381680" id="" name="Bamboutos FC"></home><away alternate_id="536380381676" id="2354870" name="APEJES Academy"></away></match><match alternate_id="" alternate_id_2="4324215" date="03.05.2015" id="" static_id="03051523390032354869" status="14:30" time="14:30"><home alternate_id="" id="2339003" name="Botafogo"></home><away alternate_id="536380381679" id="2354869" name="UMS de Loum"></away></match><match alternate_id="" alternate_id_2="4324085" date="03.05.2015" id="" static_id="" status="14:30" time="14:30"><home alternate_id="536380381681" id="2339705" name="Canon Yaounde"></home><away alternate_id="536380381677" id="" name="Njalla Quan"></away></match><match alternate_id="" alternate_id_2="4325085" date="03.05.2015" id="" static_id="" status="14:30" time="14:30"><home alternate_id="536380381682" id="2354871" name="Cosmos de Bafia"></home><away alternate_id="" id="" name="Dragon Douala"></away></match><match alternate_id="" alternate_id_2="4324203" date="03.05.2015" id="" static_id="03051523397062339704" status="14:30" time="14:30"><home alternate_id="536380381673" id="2339706" name="Cotonsport"></home><away alternate_id="536380381686" id="2339704" name="Union Douala"></away></match><match alternate_id="" alternate_id_2="4324461" date="03.05.2015" id="" static_id="03051523397022339725" status="14:30" time="14:30"><home alternate_id="536380381687" id="2339702" name="Les Astres"></home><away alternate_id="536380381674" id="2339725" name="Tonnerre"></away></match><match alternate_id="4105243" alternate_id_2="4324169" date="03.05.2015" id="4222798" static_id="03051523560982352101" status="14:30" time="14:30"><home alternate_id="" id="2356098" name="Lion Blesse"></home><away alternate_id="536380381675" id="2352101" name="New Star"></away></match><match alternate_id="" alternate_id_2="4324106" date="03.05.2015" id="" static_id="03051523397172339729" status="14:30" time="14:30"><home alternate_id="536380381672" id="2339717" name="Panthere"></home><away alternate_id="536380381688" id="2339729" name="Young Sports"></away></match><match alternate_id="4105253" alternate_id_2="4327297" date="09.05.2015" id="4222808" static_id="09051523548702339706" status="12:00" time="12:00"><home alternate_id="536380381676" id="2354870" name="APEJES Academy"></home><away alternate_id="536380381673" id="2339706" name="Cotonsport"></away></match><match alternate_id="" alternate_id_2="4327298" date="09.05.2015" id="" static_id="" status="12:00" time="12:00"><home alternate_id="" id="2339003" name="Botafogo"></home><away alternate_id="536380381680" id="" name="Bamboutos FC"></away></match><match alternate_id="" alternate_id_2="4327354" date="09.05.2015" id="" static_id="" status="12:00" time="12:00"><home alternate_id="" id="" name="Dragon Douala"></home><away alternate_id="536380381687" id="2339702" name="Les Astres"></away></match><match alternate_id="4105257" alternate_id_2="4327299" date="09.05.2015" id="4222812" static_id="09051523397122356098" status="12:00" time="12:00"><home alternate_id="536380381683" id="2339712" name="Fovu Baham"></home><away alternate_id="" id="2356098" name="Lion Blesse"></away></match><match alternate_id="" alternate_id_2="4327300" date="09.05.2015" id="" static_id="" status="12:00" time="12:00"><home alternate_id="536380381677" id="" name="Njalla Quan"></home><away alternate_id="536380381678" id="2339727" name="Bafang"></away></match><match alternate_id="" alternate_id_2="4327301" date="09.05.2015" id="" static_id="09051523397252352101" status="12:00" time="12:00"><home alternate_id="536380381674" id="2339725" name="Tonnerre"></home><away alternate_id="536380381675" id="2352101" name="New Star"></away></match><match alternate_id="4105256" alternate_id_2="4327302" date="09.05.2015" id="4222811" static_id="09051523548692339717" status="12:00" time="12:00"><home alternate_id="536380381679" id="2354869" name="UMS de Loum"></home><away alternate_id="536380381672" id="2339717" name="Panthere"></away></match><match alternate_id="" alternate_id_2="4327303" date="09.05.2015" id="" static_id="09051523397042354871" status="12:00" time="12:00"><home alternate_id="536380381686" id="2339704" name="Union Douala"></home><away alternate_id="536380381682" id="2354871" name="Cosmos de Bafia"></away></match><match alternate_id="" alternate_id_2="4327304" date="09.05.2015" id="" static_id="09051523397292339705" status="12:00" time="12:00"><home alternate_id="536380381688" id="2339729" name="Young Sports"></home><away alternate_id="536380381681" id="2339705" name="Canon Yaounde"></away></match><match alternate_id="" alternate_id_2="4329796" date="16.05.2015" id="" static_id="16051523397022339706" status="12:00" time="12:00"><home alternate_id="536380381687" id="2339702" name="Les Astres"></home><away alternate_id="536380381673" id="2339706" name="Cotonsport"></away></match><match alternate_id="" alternate_id_2="4329797" date="16.05.2015" id="" static_id="" status="12:00" time="12:00"><home alternate_id="536380381675" id="2352101" name="New Star"></home><away alternate_id="536380381677" id="" name="Njalla Quan"></away></match></league></odds_feed>