<?xml version="1.0" encoding="utf-8"?><odds_feed updated="18.08.2015 04:29:11" sport="soccer"><league country="guatemala" id="3070" name="Guatemala: Liga Nacional - Apertura" sub_id="30701"><match alternate_id="4140956" alternate_id_2="4450537" date="22.08.2015" id="4258494" static_id="22081523427722342773" status="22:00" time="22:00"><home alternate_id="536380381288" id="2342772" name="Comunicaciones"></home><away alternate_id="" id="2342773" name="Guastatoya"></away></match><match alternate_id="4140955" alternate_id_2="4450538" date="23.08.2015" id="4258493" static_id="23081523427862342790" status="02:00" time="02:00"><home alternate_id="" id="2342786" name="Petapa"></home><away alternate_id="536380382200" id="2342790" name="Suchitepequez"></away></match><match alternate_id="4140959" alternate_id_2="4450521" date="23.08.2015" id="4258497" static_id="23081523427712342780" status="17:00" time="17:00"><home alternate_id="" id="2342771" name="Cobán Imperial"></home><away alternate_id="" id="2342780" name="Marquense"></away></match><match alternate_id="4140957" alternate_id_2="4450561" date="23.08.2015" id="4258495" static_id="23081523427692337700" status="17:00" time="17:00"><home alternate_id="" id="2342769" name="Malacateco"></home><away alternate_id="" id="2337700" name="Antigua"></away></match><match alternate_id="4140960" alternate_id_2="4450544" date="23.08.2015" id="4258498" static_id="23081523427922342781" status="17:05" time="17:05"><home alternate_id="536380382204" id="2342792" name="Universidad SC"></home><away alternate_id="" id="2342781" name="Mictlan"></away></match><match alternate_id="4140958" alternate_id_2="4450522" date="23.08.2015" id="4258496" static_id="23081523427932342783" status="18:00" time="18:00"><home alternate_id="536380382205" id="2342793" name="Xelaju"></home><away alternate_id="536380382199" id="2342783" name="Municipal"></away></match><match alternate_id="" alternate_id_2="4452445" date="29.08.2015" id="" static_id="29081523427712342772" status="20:00" time="20:00"><home alternate_id="" id="2342771" name="Cobán Imperial"></home><away alternate_id="536380381288" id="2342772" name="Comunicaciones"></away></match><match alternate_id="" alternate_id_2="4452500" date="29.08.2015" id="" static_id="29081523427802342773" status="20:00" time="20:00"><home alternate_id="" id="2342780" name="Marquense"></home><away alternate_id="" id="2342773" name="Guastatoya"></away></match><match alternate_id="" alternate_id_2="4452476" date="29.08.2015" id="" static_id="29081523427812337700" status="20:00" time="20:00"><home alternate_id="" id="2342781" name="Mictlan"></home><away alternate_id="" id="2337700" name="Antigua"></away></match><match alternate_id="" alternate_id_2="4452506" date="29.08.2015" id="" static_id="29081523427832342790" status="20:00" time="20:00"><home alternate_id="536380382199" id="2342783" name="Municipal"></home><away alternate_id="536380382200" id="2342790" name="Suchitepequez"></away></match><match alternate_id="" alternate_id_2="4452477" date="29.08.2015" id="" static_id="29081523427922342769" status="20:00" time="20:00"><home alternate_id="536380382204" id="2342792" name="Universidad SC"></home><away alternate_id="" id="2342769" name="Malacateco"></away></match><match alternate_id="" alternate_id_2="4452446" date="29.08.2015" id="" static_id="29081523427932342786" status="20:00" time="20:00"><home alternate_id="536380382205" id="2342793" name="Xelaju"></home><away alternate_id="" id="2342786" name="Petapa"></away></match><match alternate_id="" alternate_id_2="4453236" date="09.09.2015" id="" static_id="09091523377002342771" status="20:00" time="20:00"><home alternate_id="" id="2337700" name="Antigua"></home><away alternate_id="" id="2342771" name="Cobán Imperial"></away></match><match alternate_id="" alternate_id_2="4453248" date="09.09.2015" id="" static_id="09091523427722342793" status="20:00" time="20:00"><home alternate_id="536380381288" id="2342772" name="Comunicaciones"></home><away alternate_id="536380382205" id="2342793" name="Xelaju"></away></match><match alternate_id="" alternate_id_2="4453228" date="09.09.2015" id="" static_id="09091523427732342783" status="20:00" time="20:00"><home alternate_id="" id="2342773" name="Guastatoya"></home><away alternate_id="536380382199" id="2342783" name="Municipal"></away></match><match alternate_id="" alternate_id_2="4453237" date="09.09.2015" id="" static_id="09091523427692342781" status="20:00" time="20:00"><home alternate_id="" id="2342769" name="Malacateco"></home><away alternate_id="" id="2342781" name="Mictlan"></away></match><match alternate_id="" alternate_id_2="4453229" date="09.09.2015" id="" static_id="09091523427862342780" status="20:00" time="20:00"><home alternate_id="" id="2342786" name="Petapa"></home><away alternate_id="" id="2342780" name="Marquense"></away></match><match alternate_id="" alternate_id_2="4453239" date="09.09.2015" id="" static_id="09091523427902342792" status="20:00" time="20:00"><home alternate_id="536380382200" id="2342790" name="Suchitepequez"></home><away alternate_id="536380382204" id="2342792" name="Universidad SC"></away></match><match alternate_id="" alternate_id_2="4454483" date="12.09.2015" id="" static_id="12091523427812342790" status="20:00" time="20:00"><home alternate_id="" id="2342781" name="Mictlan"></home><away alternate_id="536380382200" id="2342790" name="Suchitepequez"></away></match><match alternate_id="" alternate_id_2="4454504" date="12.09.2015" id="" static_id="12091523427922342773" status="20:00" time="20:00"><home alternate_id="536380382204" id="2342792" name="Universidad SC"></home><away alternate_id="" id="2342773" name="Guastatoya"></away></match></league></odds_feed>