<?xml version="1.0" encoding="utf-8"?><odds_feed updated="01.05.2015 00:17:08" sport="soccer"><league country="honduras" cup="False" id="3075" name="Honduras: Liga Nacional - Clausura" sub_id="30752"><match alternate_id="" alternate_id_2="4325469" date="02.05.2015" id="" static_id="02051523392962337866" status="Postp." time="21:30"><home alternate_id="536380382207" id="2339296" name="Olimpia"></home><away alternate_id="536380381298" id="2337866" name="Platense"></away><odds></odds></match><match alternate_id="4093536" alternate_id_2="4325470" date="02.05.2015" id="4211102" static_id="02051523541042342859" status="Postp." time="21:30"><home alternate_id="" id="2354104" name="Parrillas O."></home><away alternate_id="" id="2342859" name="Victoria"></away><odds></odds></match><match alternate_id="4093688" alternate_id_2="4325471" date="02.05.2015" id="4211254" static_id="02051523428562355506" status="Postp." time="21:30"><home alternate_id="" id="2342856" name="Real Espana"></home><away alternate_id="" id="2355506" name="CD Honduras"></away><odds></odds></match><match alternate_id="4093535" alternate_id_2="4324980" date="02.05.2015" id="4211101" static_id="02051523479502342853" status="Postp." time="21:30"><home alternate_id="53638038902" id="2347950" name="Real Sociedad"></home><away alternate_id="" id="2342853" name="Motagua"></away><odds></odds></match><match alternate_id="4093537" alternate_id_2="4325472" date="02.05.2015" id="4211103" static_id="02051523428602342852" status="Postp." time="21:30"><home alternate_id="" id="2342860" name="Vida"></home><away alternate_id="536380382206" id="2342852" name="Marathon"></away><odds></odds></match></league></odds_feed>