<?xml version="1.0" encoding="utf-8"?><recent_results updated="14.11.2015 13:41:33" sport="soccer" country="newzealand"><league country="newzealand" name="New Zealand: Football Championship" cup="False" id="3157" sub_id="31570"><match alternate_id="4214244" alternate_id_2="4463181" date="12.11.2015" id="4331745" static_id="12111523453632345371" status="FT" time="06:35">
<home goals="1" id="2345363" name="Auckland City"></home>
<away goals="1" id="2345371" name="Hawke's Bay"></away>
<events>
<event id="23645314" minute="11" player="M. Lea`alafa" playerid="" result="[1 - 0]" team="home" type="goal"></event>
<event id="23645315" minute="85" player="K. Matsumoto" playerid="" result="[1 - 1]" team="away" type="goal"></event>
</events>
<ht score="[1-0]"></ht>
</match><match alternate_id="4214243" alternate_id_2="4463180" date="08.11.2015" id="4331744" static_id="08111523453822345363" status="FT" time="03:35">
<home goals="0" id="2345382" name="Waitakere United"></home>
<away goals="4" id="2345363" name="Auckland City"></away>
<events>
<event id="23645304" minute="76" player="J. Moreira" playerid="2348971" result="[0 - 1]" team="away" type="goal"></event>
<event id="23645305" minute="79" player="M. Lea`alafa" playerid="" result="[0 - 2]" team="away" type="goal"></event>
<event id="23645306" minute="84" player="R. de Vries" playerid="2436819" result="[0 - 3]" team="away" type="goal"></event>
<event id="23645307" minute="87" player="M. Lea`alafa" playerid="" result="[0 - 4]" team="away" type="goal"></event>
</events>
<ht score="[0-0]"></ht>
</match></league><league country="newzealand" name="New Zealand: Football Championship - Play Offs" cup="False" id="3157" sub_id="31573"><match alternate_id="4118108" alternate_id_2="4320908" date="05.04.2015" id="4235652" static_id="05041523453632345371" status="FT" time="02:00">
<home goals="2" id="2345363" name="Auckland City"></home>
<away goals="1" id="2345371" name="Hawke's Bay"></away>
<events>
<event id="22222584" minute="19" player="R. Tinsley (pen.)" playerid="" result="[0 - 1]" team="away" type="goal"></event>
<event id="22222585" minute="38" player="R. de Vries" playerid="2436819" result="[1 - 1]" team="home" type="goal"></event>
<event id="22222586" minute="62" player="M. Dordevic" playerid="2379067" result="[2 - 1]" team="home" type="goal"></event>
</events>
<ht score="[1-1]"></ht>
</match><match alternate_id="4115167" alternate_id_2="4317638" date="29.03.2015" id="4232715" static_id="29031523453632345382" status="FT" time="01:00">
<home goals="5" id="2345363" name="Auckland City"></home>
<away goals="1" id="2345382" name="Waitakere United"></away>
<events>
<event id="22189884" minute="13" player="D. Browne" playerid="2505177" result="[1 - 0]" team="home" type="goal"></event>
<event id="22189885" minute="15" player="D. Browne" playerid="2505177" result="[2 - 0]" team="home" type="goal"></event>
<event id="22189886" minute="17" player="J. Moreira" playerid="2348971" result="[3 - 0]" team="home" type="goal"></event>
<event id="22189887" minute="60" player="D. Browne" playerid="2505177" result="[4 - 0]" team="home" type="goal"></event>
<event id="22189888" minute="63" player="D. Richards" playerid="2721342" result="[4 - 1]" team="away" type="goal"></event>
<event id="22189889" minute="71" player="O. Garcia" playerid="2443602" result="[5 - 1]" team="home" type="goal"></event>
</events>
<ht score="[3-0]"></ht>
</match><match alternate_id="4115168" alternate_id_2="4317639" date="29.03.2015" id="4232716" static_id="29031523453802345371" status="FT" time="00:00">
<home goals="3" id="2345380" name="Team Wellington"></home>
<away goals="4" id="2345371" name="Hawke's Bay"></away>
<events>
<event id="22189894" minute="8" player="S. Lovemore" playerid="" result="[0 - 1]" team="away" type="goal"></event>
<event id="22189895" minute="16" player="T. Myers" playerid="2436817" result="[1 - 1]" team="home" type="goal"></event>
<event id="22189896" minute="27" player="R. Tinsley (pen.)" playerid="" result="[1 - 2]" team="away" type="goal"></event>
<event id="22189897" minute="36" player="I. Hogg" playerid="" result="[2 - 2]" team="home" type="goal"></event>
<event id="22189898" minute="47" player="J. B. San Facundo" playerid="" result="[2 - 3]" team="away" type="goal"></event>
<event id="22189899" minute="66" player="B. Robertson" playerid="2403229" result="[3 - 3]" team="home" type="goal"></event>
<event id="22189900" minute="71" player="R. Tinsley (pen.)" playerid="" result="[3 - 4]" team="away" type="goal"></event>
<event id="22189901" minute="90" player="A. Feneridis" playerid="2354060" result="" team="home" type="redcard"></event>
</events>
<ht score="[2-2]"></ht>
</match><match alternate_id="4115165" alternate_id_2="4317636" date="21.03.2015" id="4232713" static_id="21031523453712345380" status="FT" time="04:00">
<home goals="1" id="2345371" name="Hawke's Bay"></home>
<away goals="2" id="2345380" name="Team Wellington"></away>
<events>
<event id="22189864" minute="8" player="H. Faarodo" playerid="" result="[0 - 1]" team="away" type="goal"></event>
<event id="22189865" minute="35" player="S. Halpin (pen.)" playerid="" result="[1 - 1]" team="home" type="goal"></event>
<event id="22189866" minute="77" player="H. Faarodo" playerid="" result="[1 - 2]" team="away" type="goal"></event>
</events>
<ht score="[1-1]"></ht>
</match><match alternate_id="4115166" alternate_id_2="4317637" date="21.03.2015" id="4232714" static_id="21031523453822345363" status="FT" time="01:00">
<home goals="0" id="2345382" name="Waitakere United"></home>
<away goals="2" id="2345363" name="Auckland City"></away>
<events>
<event id="22189874" minute="27" player="R. de Vries" playerid="2436819" result="[0 - 1]" team="away" type="goal"></event>
<event id="22189875" minute="44" player="O. Garcia" playerid="2443602" result="[0 - 2]" team="away" type="goal"></event>
</events>
<ht score="[0-2]"></ht>
</match></league><league country="newzealand" name="New Zealand: Football Championship" cup="False" id="3157" sub_id="31570"><match alternate_id="4080237" alternate_id_2="4307810" date="15.03.2015" id="4197827" static_id="15031523453712353995" status="FT" time="01:00">
<home goals="5" id="2345371" name="Hawke's Bay"></home>
<away goals="2" id="2353995" name="Canterbury"></away>
<events>
<event id="22091604" minute="3" player="S. Lovemore" playerid="" result="[1 - 0]" team="home" type="goal"></event>
<event id="22091605" minute="6" player="A. Clapham (pen.)" playerid="" result="[1 - 1]" team="away" type="goal"></event>
<event id="22091606" minute="14" player="A. Spain" playerid="" result="[1 - 2]" team="away" type="goal"></event>
<event id="22091607" minute="16" player="S. Lovemore" playerid="" result="[2 - 2]" team="home" type="goal"></event>
<event id="22091608" minute="23" player="R. Tinsley" playerid="" result="[3 - 2]" team="home" type="goal"></event>
<event id="22091609" minute="77" player="S. Lovemore" playerid="" result="[4 - 2]" team="home" type="goal"></event>
<event id="22091610" minute="90" player="R. Haviland" playerid="2496105" result="[5 - 2]" team="home" type="goal"></event>
</events>
<ht score="[3-2]"></ht>
</match><match alternate_id="4079166" alternate_id_2="4307809" date="14.03.2015" id="4196761" static_id="14031523453812345377" status="FT" time="04:00">
<home goals="2" id="2345381" name="WaiBOP"></home>
<away goals="1" id="2345377" name="Southern United"></away>
<events>
<event id="22091594" minute="38" player="T. McLennan" playerid="" result="[0 - 1]" team="away" type="goal"></event>
<event id="22091595" minute="62" player="R. Greenhalgh (pen.)" playerid="2612111" result="[1 - 1]" team="home" type="goal"></event>
<event id="22091596" minute="74" player="S. Young" playerid="" result="[2 - 1]" team="home" type="goal"></event>
</events>
<ht score="[0-1]"></ht>
</match><match alternate_id="4079165" alternate_id_2="4307807" date="14.03.2015" id="4196760" static_id="14031523453822345380" status="FT" time="01:00">
<home goals="4" id="2345382" name="Waitakere United"></home>
<away goals="0" id="2345380" name="Team Wellington"></away>
<events>
<event id="22091574" minute="5" player="N. Bowen" playerid="2726387" result="[1 - 0]" team="home" type="goal"></event>
<event id="22091575" minute="16" player="T. Biss" playerid="2501538" result="[2 - 0]" team="home" type="goal"></event>
<event id="22091576" minute="35" player="D. Richards" playerid="2721342" result="[3 - 0]" team="home" type="goal"></event>
<event id="22091577" minute="75" player="D. Richards" playerid="2721342" result="[4 - 0]" team="home" type="goal"></event>
</events>
<ht score="[3-0]"></ht>
</match><match alternate_id="4079164" alternate_id_2="4307808" date="14.03.2015" id="4196759" static_id="14031523558972345363" status="FT" time="01:00">
<home goals="0" id="2355897" name="Wellington Phoenix Res"></home>
<away goals="7" id="2345363" name="Auckland City"></away>
<events>
<event id="22091584" minute="20" player="R. de Vries" playerid="2436819" result="[0 - 1]" team="away" type="goal"></event>
<event id="22091585" minute="24" player="O. Garcia" playerid="2443602" result="[0 - 2]" team="away" type="goal"></event>
<event id="22091586" minute="32" player="J. Moreira (pen.)" playerid="2348971" result="[0 - 3]" team="away" type="goal"></event>
<event id="22091587" minute="43" player="J. Moreira" playerid="2348971" result="[0 - 4]" team="away" type="goal"></event>
<event id="22091588" minute="55" player="I. Carril" playerid="2393504" result="[0 - 5]" team="away" type="goal"></event>
<event id="22091589" minute="60" player="R. de Vries" playerid="2436819" result="[0 - 6]" team="away" type="goal"></event>
<event id="22091590" minute="73" player="A. Milne" playerid="2491536" result="[0 - 7]" team="away" type="goal"></event>
</events>
<ht score="[0-4]"></ht>
</match><match alternate_id="4079161" alternate_id_2="4305978" date="08.03.2015" id="4196756" static_id="08031523453712345381" status="FT" time="02:00">
<home goals="0" id="2345371" name="Hawke's Bay"></home>
<away goals="1" id="2345381" name="WaiBOP"></away>
<events>
<event id="22073284" minute="90" player="F. Marquez" playerid="" result="[0 - 1]" team="away" type="goal"></event>
</events>
<ht score="[0-0]"></ht>
</match><match alternate_id="4079163" alternate_id_2="4305701" date="08.03.2015" id="4196758" static_id="08031523453632345382" status="FT" time="01:00">
<home goals="1" id="2345363" name="Auckland City"></home>
<away goals="0" id="2345382" name="Waitakere United"></away>
<events>
<event id="22070514" minute="9" player="I. Carril" playerid="2393504" result="[1 - 0]" team="home" type="goal"></event>
<event id="22070515" minute="86" player="A. Solomons" playerid="2503725" result="" team="away" type="yellowred"></event>
</events>
<ht score="[1-0]"></ht>
</match><match alternate_id="4079162" alternate_id_2="4305737" date="08.03.2015" id="4196757" static_id="08031523453772349270" status="FT" time="01:00">
<home goals="1" id="2345377" name="Southern United"></home>
<away goals="0" id="2349270" name="Wanderers"></away>
<events>
<event id="22070874" minute="64" player="A. Mitchell" playerid="" result="" team="away" type="redcard"></event>
<event id="22070875" minute="65" player="T. Jackson (pen.)" playerid="" result="[1 - 0]" team="home" type="goal"></event>
</events>
<ht score="[0-0]"></ht>
</match><match alternate_id="4101637" alternate_id_2="4305702" date="07.03.2015" id="4219195" static_id="07031523558972353995" status="FT" time="01:00">
<home goals="2" id="2355897" name="Wellington Phoenix Res"></home>
<away goals="1" id="2353995" name="Canterbury"></away>
<events>
<event id="22070524" minute="51" player="J. Stevens (pen.)" playerid="" result="[1 - 0]" team="home" type="goal"></event>
<event id="22070525" minute="56" player="A. Spain" playerid="" result="[1 - 1]" team="away" type="goal"></event>
<event id="22070526" minute="74" player="X. Pratt" playerid="" result="[2 - 1]" team="home" type="goal"></event>
</events>
<ht score="[0-0]"></ht>
</match><match alternate_id="4079159" alternate_id_2="4304318" date="01.03.2015" id="4196754" static_id="01031523453802349270" status="FT" time="02:00">
<home goals="1" id="2345380" name="Team Wellington"></home>
<away goals="1" id="2349270" name="Wanderers"></away>
<events>
<event id="22056684" minute="13" player="B. Robertson" playerid="2403229" result="[1 - 0]" team="home" type="goal"></event>
<event id="22056685" minute="45" player="C. Maukau-McPhee" playerid="" result="[1 - 1]" team="away" type="goal"></event>
</events>
<ht score="[1-1]"></ht>
</match><match alternate_id="4107732" alternate_id_2="4309189" date="01.03.2015" id="4225286" static_id="01031523453772345371" status="FT" time="00:00">
<home goals="1" id="2345377" name="Southern United"></home>
<away goals="2" id="2345371" name="Hawke's Bay"></away>
<events>
<event id="22105394" minute="1" player="A. Ridden" playerid="2558389" result="[1 - 0]" team="home" type="goal"></event>
<event id="22105395" minute="10" player="V. Lekaj" playerid="" result="[1 - 1]" team="away" type="goal"></event>
<event id="22105396" minute="55" player="R. Tinsley (pen.)" playerid="" result="[1 - 2]" team="away" type="goal"></event>
</events>
<ht score="[1-1]"></ht>
</match><match alternate_id="4079157" alternate_id_2="4304317" date="28.02.2015" id="4196752" static_id="28021523453812355897" status="FT" time="02:00">
<home goals="2" id="2345381" name="WaiBOP"></home>
<away goals="3" id="2355897" name="Wellington Phoenix Res"></away>
<events>
<event id="22056674" minute="35" player="C. Coombes" playerid="" result="[1 - 0]" team="home" type="goal"></event>
<event id="22056675" minute="43" player="C. Coombes" playerid="" result="[2 - 0]" team="home" type="goal"></event>
<event id="22056676" minute="45" player="A. Blake" playerid="" result="[2 - 1]" team="away" type="goal"></event>
<event id="22056677" minute="76" player="C. Fleury" playerid="" result="[2 - 2]" team="away" type="goal"></event>
<event id="22056678" minute="88" player="J. Stevens" playerid="" result="[2 - 3]" team="away" type="goal"></event>
</events>
<ht score="[2-1]"></ht>
</match><match alternate_id="4110302" alternate_id_2="4304316" date="28.02.2015" id="4227854" static_id="28021523539952345382" status="FT" time="01:00">
<home goals="1" id="2353995" name="Canterbury"></home>
<away goals="2" id="2345382" name="Waitakere United"></away>
<events>
<event id="22056664" minute="53" player="D. Richards" playerid="2721342" result="[0 - 1]" team="away" type="goal"></event>
<event id="22056665" minute="60" player="D. Richards" playerid="2721342" result="[0 - 2]" team="away" type="goal"></event>
<event id="22056666" minute="87" player="D. Terris" playerid="" result="[1 - 2]" team="home" type="goal"></event>
</events>
<ht score="[0-0]"></ht>
</match><match alternate_id="4109131" alternate_id_2="4302938" date="22.02.2015" id="4226683" static_id="22021523453632353995" status="FT" time="01:00">
<home goals="3" id="2345363" name="Auckland City"></home>
<away goals="1" id="2353995" name="Canterbury"></away>
<events>
<event id="22042884" minute="16" player="M. Peers" playerid="" result="[0 - 1]" team="away" type="goal"></event>
<event id="22042885" minute="31" player="I. Carril" playerid="2393504" result="[1 - 1]" team="home" type="goal"></event>
<event id="22042886" minute="55" player="O. Garcia (pen.)" playerid="2443602" result="[2 - 1]" team="home" type="goal"></event>
<event id="22042887" minute="66" player="J. Moreira" playerid="2348971" result="[3 - 1]" team="home" type="goal"></event>
</events>
<ht score="[1-1]"></ht>
</match><match alternate_id="4079154" alternate_id_2="4302883" date="22.02.2015" id="4196749" static_id="22021523453772345380" status="FT" time="01:00">
<home goals="1" id="2345377" name="Southern United"></home>
<away goals="2" id="2345380" name="Team Wellington"></away>
<events>
<event id="22042334" minute="34" player="J. Smith (pen.)" playerid="2360060" result="[0 - 1]" team="away" type="goal"></event>
<event id="22042335" minute="43" player="T. Jackson" playerid="" result="[1 - 1]" team="home" type="goal"></event>
<event id="22042336" minute="54" player="M. Gwyther" playerid="2436357" result="[1 - 2]" team="away" type="goal"></event>
</events>
<ht score="[1-1]"></ht>
</match><match alternate_id="4079153" alternate_id_2="4302559" date="21.02.2015" id="4196748" static_id="21021523453822345381" status="FT" time="01:00">
<home goals="2" id="2345382" name="Waitakere United"></home>
<away goals="1" id="2345381" name="WaiBOP"></away>
<events>
<event id="22039094" minute="14" player="C. Coombes" playerid="" result="[0 - 1]" team="away" type="goal"></event>
<event id="22039095" minute="23" player="T. Biss" playerid="2501538" result="[1 - 1]" team="home" type="goal"></event>
<event id="22039096" minute="90" player="D. Richards" playerid="2721342" result="[2 - 1]" team="home" type="goal"></event>
</events>
<ht score="[1-1]"></ht>
</match><match alternate_id="4079152" alternate_id_2="4302558" date="21.02.2015" id="4196747" static_id="21021523558972345371" status="FT" time="00:30">
<home goals="2" id="2355897" name="Wellington Phoenix Res"></home>
<away goals="4" id="2345371" name="Hawke's Bay"></away>
<events>
<event id="22039084" minute="5" player="C. Fleury" playerid="" result="[1 - 0]" team="home" type="goal"></event>
<event id="22039085" minute="51" player="S. Lovemore" playerid="" result="[1 - 1]" team="away" type="goal"></event>
<event id="22039086" minute="62" player="N. Hailemariam" playerid="" result="[2 - 1]" team="home" type="goal"></event>
<event id="22039087" minute="63" player="V. Lekaj" playerid="" result="[2 - 2]" team="away" type="goal"></event>
<event id="22039088" minute="66" player="R. Tinsley (pen.)" playerid="" result="[2 - 3]" team="away" type="goal"></event>
<event id="22039089" minute="79" player="S. Lovemore" playerid="" result="[2 - 4]" team="away" type="goal"></event>
</events>
<ht score="[1-0]"></ht>
</match><match alternate_id="4101636" alternate_id_2="4301767" date="18.02.2015" id="4219194" static_id="18021523453812345363" status="FT" time="05:00">
<home goals="0" id="2345381" name="WaiBOP"></home>
<away goals="2" id="2345363" name="Auckland City"></away>
<events>
<event id="22031174" minute="28" player="D. Browne" playerid="2505177" result="[0 - 1]" team="away" type="goal"></event>
<event id="22031175" minute="90" player="S. Burfoot" playerid="2653998" result="[0 - 2]" team="away" type="goal"></event>
</events>
<ht score="[0-1]"></ht>
</match><match alternate_id="4079149" alternate_id_2="4302557" date="15.02.2015" id="4196744" static_id="15021523453712345382" status="FT" time="01:15">
<home goals="3" id="2345371" name="Hawke's Bay"></home>
<away goals="2" id="2345382" name="Waitakere United"></away>
<events>
<event id="22039074" minute="8" player="N. Bowen" playerid="2726387" result="[0 - 1]" team="away" type="goal"></event>
<event id="22039075" minute="10" player="S. Lovemore" playerid="" result="[1 - 1]" team="home" type="goal"></event>
<event id="22039076" minute="49" player="S. Lovemore" playerid="" result="[2 - 1]" team="home" type="goal"></event>
<event id="22039077" minute="62" player="A. Palezevic" playerid="" result="[3 - 1]" team="home" type="goal"></event>
<event id="22039078" minute="72" player="N. Bowen" playerid="2726387" result="[3 - 2]" team="away" type="goal"></event>
<event id="22039079" minute="85" player="G. Darkwa" playerid="2722806" result="" team="away" type="redcard"></event>
<event id="22039080" minute="90" player="D. Mulligan" playerid="2347378" result="" team="away" type="redcard"></event>
</events>
<ht score="[1-1]"></ht>
</match></league></recent_results>