<?xml version="1.0" encoding="utf-8"?><fixtures updated="17.08.2015 06:50:42" sport="soccer" country="moldova"><league country="moldova" name="Moldova: Divizia Nationala" cup="False" id="3143" sub_id="31430"><match alternate_id="4159229" alternate_id_2="4410207" date="22.08.2015" id="4276755" static_id="22081523514472344861" status="14:00" time="14:00">
<home id="2351447" name="Ceadir Lunga"></home>
<away id="2344861" name="Zaria Balti"></away>


</match><match alternate_id="4159230" alternate_id_2="4410208" date="22.08.2015" id="4276756" static_id="22081523448652349789" status="14:00" time="14:00">
<home id="2344865" name="Petrocub"></home>
<away id="2349789" name="Dinamo-Auto"></away>


</match><match alternate_id="4159231" alternate_id_2="4410209" date="22.08.2015" id="4276757" static_id="22081523448692344881" status="16:00" time="16:00">
<home id="2344869" name="Sheriff Tiraspol"></home>
<away id="2344881" name="Milsami"></away>


</match><match alternate_id="4159232" alternate_id_2="4410669" date="23.08.2015" id="4276758" static_id="23081523448302344817" status="14:00" time="14:00">
<home id="2344830" name="Dacia Chisinau"></home>
<away id="2344817" name="Academia Chisinau"></away>


</match><match alternate_id="4159233" alternate_id_2="4410670" date="23.08.2015" id="4276759" static_id="23081523448712344882" status="14:00" time="14:00">
<home id="2344871" name="Speranta Nisporeni"></home>
<away id="2344882" name="Zimbru Chisinau"></away>


</match><match alternate_id="4159234" alternate_id_2="4441061" date="28.08.2015" id="4276760" static_id="28081523497892344871" status="14:00" time="14:00">
<home id="2349789" name="Dinamo-Auto"></home>
<away id="2344871" name="Speranta Nisporeni"></away>


</match><match alternate_id="4159235" alternate_id_2="4441062" date="28.08.2015" id="4276761" static_id="28081523448612344865" status="14:00" time="14:00">
<home id="2344861" name="Zaria Balti"></home>
<away id="2344865" name="Petrocub"></away>


</match><match alternate_id="4159236" alternate_id_2="4441063" date="29.08.2015" id="4276762" static_id="29081523448172344881" status="14:00" time="14:00">
<home id="2344817" name="Academia Chisinau"></home>
<away id="2344881" name="Milsami"></away>


</match><match alternate_id="4159237" alternate_id_2="4441696" date="29.08.2015" id="4276763" static_id="29081523448302351447" status="14:00" time="14:00">
<home id="2344830" name="Dacia Chisinau"></home>
<away id="2351447" name="Ceadir Lunga"></away>


</match><match alternate_id="4159238" alternate_id_2="4450523" date="29.08.2015" id="4276764" static_id="29081523448822344869" status="17:00" time="17:00">
<home id="2344882" name="Zimbru Chisinau"></home>
<away id="2344869" name="Sheriff Tiraspol"></away>


</match><match alternate_id="4159239" alternate_id_2="4452110" date="12.09.2015" id="4276765" static_id="12091523514472344817" status="13:00" time="13:00">
<home id="2351447" name="Ceadir Lunga"></home>
<away id="2344817" name="Academia Chisinau"></away>


</match><match alternate_id="4159240" alternate_id_2="4452161" date="12.09.2015" id="4276766" static_id="12091523448712344861" status="13:00" time="13:00">
<home id="2344871" name="Speranta Nisporeni"></home>
<away id="2344861" name="Zaria Balti"></away>


</match><match alternate_id="4159242" alternate_id_2="4452447" date="13.09.2015" id="4276768" static_id="13091523448812344882" status="13:00" time="13:00">
<home id="2344881" name="Milsami"></home>
<away id="2344882" name="Zimbru Chisinau"></away>


</match><match alternate_id="4159241" alternate_id_2="4452448" date="13.09.2015" id="4276767" static_id="13091523448652344830" status="13:00" time="13:00">
<home id="2344865" name="Petrocub"></home>
<away id="2344830" name="Dacia Chisinau"></away>


</match><match alternate_id="4159243" alternate_id_2="4452449" date="13.09.2015" id="4276769" static_id="13091523448692349789" status="15:00" time="15:00">
<home id="2344869" name="Sheriff Tiraspol"></home>
<away id="2349789" name="Dinamo-Auto"></away>


</match><match alternate_id="4159244" alternate_id_2="4454077" date="18.09.2015" id="4276770" static_id="18091523448172344882" status="13:00" time="13:00">
<home id="2344817" name="Academia Chisinau"></home>
<away id="2344882" name="Zimbru Chisinau"></away>


</match><match alternate_id="4159245" alternate_id_2="4454078" date="18.09.2015" id="4276771" static_id="18091523497892344881" status="13:00" time="13:00">
<home id="2349789" name="Dinamo-Auto"></home>
<away id="2344881" name="Milsami"></away>


</match><match alternate_id="4159248" alternate_id_2="4454079" date="19.09.2015" id="4276774" static_id="19091523514472344865" status="13:00" time="13:00">
<home id="2351447" name="Ceadir Lunga"></home>
<away id="2344865" name="Petrocub"></away>


</match><match alternate_id="4159247" alternate_id_2="4454080" date="19.09.2015" id="4276773" static_id="19091523448302344871" status="13:00" time="13:00">
<home id="2344830" name="Dacia Chisinau"></home>
<away id="2344871" name="Speranta Nisporeni"></away>


</match><match alternate_id="4159246" alternate_id_2="4454108" date="19.09.2015" id="4276772" static_id="19091523448612344869" status="13:00" time="13:00">
<home id="2344861" name="Zaria Balti"></home>
<away id="2344869" name="Sheriff Tiraspol"></away>


</match></league></fixtures>